attribution/__init__.py
attribution/utils.py
attribution/citation_methods/__init__.py
attribution/citation_methods/embedding_based_citation.py
attribution/citation_methods/llm_based_citation.py
attribution_lib-0.4.0.dist-info/licenses/LICENSE
attribution_lib-0.4.0.dist-info/METADATA
attribution_lib-0.4.0.dist-info/WHEEL
attribution_lib-0.4.0.dist-info/top_level.txt
attribution_lib-0.4.0.dist-info/RECORD
