Metadata-Version: 2.4
Name: attribution-lib
Version: 0.4.0
Summary: A library for constructing citable prompts and attributing contributions of context sources in RAG systems
Home-page: https://github.com/siddhant230/Attribution_package
Author: Siddhant Rai
Author-email: rsiddhant73@gmail.com
Project-URL: Bug Tracker, https://github.com/siddhant230/Attribution_package/issues
Project-URL: Documentation, https://github.com/siddhant230/Attribution_package#readme
Project-URL: Source Code, https://github.com/siddhant230/Attribution_package
Keywords: rag,attribution,citation,llm,embeddings,nlp
Classifier: Development Status :: 3 - Alpha
Classifier: Intended Audience :: Developers
Classifier: Intended Audience :: Science/Research
Classifier: License :: OSI Approved :: MIT License
Classifier: Operating System :: OS Independent
Classifier: Programming Language :: Python :: 3
Classifier: Programming Language :: Python :: 3.8
Classifier: Programming Language :: Python :: 3.9
Classifier: Programming Language :: Python :: 3.10
Classifier: Programming Language :: Python :: 3.11
Classifier: Programming Language :: Python :: 3.12
Classifier: Topic :: Scientific/Engineering :: Artificial Intelligence
Classifier: Topic :: Text Processing :: Linguistic
Requires-Python: >=3.8
License-File: LICENSE
Requires-Dist: pandas>=1.0.0
Requires-Dist: dspy-ai>=2.0.0
Requires-Dist: nltk>=3.6.0
Requires-Dist: scikit-learn>=1.0.0
Requires-Dist: fastembed>=0.2.0
Requires-Dist: python-dotenv>=0.19.0
Requires-Dist: pytest
Provides-Extra: dev
Requires-Dist: pytest>=7.0.0; extra == "dev"
Requires-Dist: pytest-cov>=4.0.0; extra == "dev"
Requires-Dist: black>=23.0.0; extra == "dev"
Requires-Dist: isort>=5.12.0; extra == "dev"
Requires-Dist: mypy>=1.0.0; extra == "dev"
Dynamic: author
Dynamic: author-email
Dynamic: classifier
Dynamic: description
Dynamic: description-content-type
Dynamic: home-page
Dynamic: keywords
Dynamic: license-file
Dynamic: project-url
Dynamic: provides-extra
Dynamic: requires-dist
Dynamic: requires-python
Dynamic: summary
